quick_python_logging/__init__.py
quick_python_logging/core.py
quick_python_logging-0.0.1.dist-info/METADATA
quick_python_logging-0.0.1.dist-info/WHEEL
quick_python_logging-0.0.1.dist-info/licenses/LICENSE
quick_python_logging-0.0.1.dist-info/RECORD
