Metadata-Version: 2.4
Name: quick_python_logging
Version: 0.0.1
Summary: LogIt - The best python logging package
Author-email: Alex Dickens <alxdickens@gmail.com>
License-Expression: MIT
License-File: LICENSE
Classifier: Operating System :: OS Independent
Classifier: Programming Language :: Python :: 3
Requires-Python: >=3.8
